cubelib/__init__.py
cubelib/enums.py
cubelib/errors.py
cubelib/iautil.py
cubelib/mcenums.py
cubelib/mcsr.py
cubelib/p.py
cubelib/types.py
cubelib/aio/__init__.py
cubelib/aio/aio.py
cubelib/proto/__init__.py
cubelib/proto/v340/ClientBound.py
cubelib/proto/v340/ServerBound.py
cubelib/proto/v340/__init__.py
cubelib/proto/v47/ClientBound.py
cubelib/proto/v47/ServerBound.py
cubelib/proto/v47/__init__.py
cubelib/proto/v47/enums.py
cubelib/proto/v47/types.py
cubelib/proto/version_independent/ClientBound.py
cubelib/proto/version_independent/ServerBound.py
cubelib/proto/version_independent/__init__.py
cubelib-1.0.9.dist-info/LICENSE
cubelib-1.0.9.dist-info/METADATA
cubelib-1.0.9.dist-info/WHEEL
cubelib-1.0.9.dist-info/entry_points.txt
cubelib-1.0.9.dist-info/top_level.txt
cubelib-1.0.9.dist-info/RECORD
