Metadata-Version: 2.1
Name: cubelib
Version: 1.0.9
Summary: python library for building/parsing minecraft protocol packets
Home-page: https://gitlab.com/seeklay/cubelib
Author: seeklay
Author-email: rudeboy@seeklay.icu
License: GNU General Public License v3.0
Download-URL: https://gitlab.com/seeklay/cubelib
Platform: OS Independent
Classifier: Programming Language :: Python :: 3.7
Classifier: Programming Language :: Python :: Implementation :: CPython
Classifier: Programming Language :: Python :: Implementation :: PyPy
Classifier: License :: OSI Approved :: GNU General Public License v3 (GPLv3)
Classifier: Operating System :: OS Independent
Classifier: Topic :: Internet
Requires-Dist: NBT
